shapley_calculator/__init__.py
shapley_calculator/shapley.py
shapley_calculator/utils.py
shapley_calculator-0.1.1.dist-info/LICENSE
shapley_calculator-0.1.1.dist-info/METADATA
shapley_calculator-0.1.1.dist-info/WHEEL
shapley_calculator-0.1.1.dist-info/top_level.txt
shapley_calculator-0.1.1.dist-info/RECORD
