Metadata-Version: 2.2
Name: shapley_calculator
Version: 0.1.1
Summary: A library to calculate Shapley values for feature importance in machine learning models.
Home-page: https://github.com/AlekseevDS21/Shapley
Author: Andrew Alexeev
Author-email: andrey.alekseev8996@gmail.com
Classifier: Programming Language :: Python :: 3
Classifier: License :: OSI Approved :: MIT License
Classifier: Operating System :: OS Independent
Requires-Python: >=3.6
License-File: LICENSE
Dynamic: author
Dynamic: author-email
Dynamic: classifier
Dynamic: description
Dynamic: description-content-type
Dynamic: home-page
Dynamic: requires-python
Dynamic: summary
